scan_metadata_processor/__about__.py
scan_metadata_processor/__init__.py
scan_metadata_processor/cli.py
scan_metadata_processor/commands/__init__.py
scan_metadata_processor/commands/cli_check.py
scan_metadata_processor/commands/cli_clean.py
scan_metadata_processor/commands/cli_process.py
scan_metadata_processor/comparator/__init__.py
scan_metadata_processor/comparator/metadata_comparator.py
scan_metadata_processor/converter/__init__.py
scan_metadata_processor/converter/lookup_to_isogeo.py
scan_metadata_processor/converter/matchers/__init__.py
scan_metadata_processor/converter/matchers/matcher_formats.py
scan_metadata_processor/converter/matchers/matcher_geometry_types.py
scan_metadata_processor/converter/matchers/matcher_srs.py
scan_metadata_processor/database/__init__.py
scan_metadata_processor/database/elasticsearch/__init__.py
scan_metadata_processor/database/elasticsearch/mngr_elastic_search.py
scan_metadata_processor/database/isogeo/__init__.py
scan_metadata_processor/database/isogeo/metadata_synchronizer.py
scan_metadata_processor/i18n/fr_FR/LC_MESSAGES/scan_metadata_processor.mo
scan_metadata_processor/i18n/fr_FR/LC_MESSAGES/scan_metadata_processor.po
scan_metadata_processor/parser/__init__.py
scan_metadata_processor/parser/json_parser.py
scan_metadata_processor/parser/zip_parser.py
scan_metadata_processor/parser/models/__init__.py
scan_metadata_processor/parser/models/listing.py
scan_metadata_processor/parser/models/lookup.py
scan_metadata_processor/parser/models/sign.py
scan_metadata_processor/utils/__init__.py
scan_metadata_processor/utils/bouncer.py
scan_metadata_processor/utils/localizer.py
scan_metadata_processor/utils/proxies.py
scan_metadata_processor/utils/slugger.py
isogeo_scan_metadata_processor-1.1.1.dist-info/METADATA
isogeo_scan_metadata_processor-1.1.1.dist-info/WHEEL
isogeo_scan_metadata_processor-1.1.1.dist-info/entry_points.txt
isogeo_scan_metadata_processor-1.1.1.dist-info/top_level.txt
isogeo_scan_metadata_processor-1.1.1.dist-info/RECORD
