Metadata-Version: 2.1
Name: isogeo-scan-metadata-processor
Version: 1.1.1
Summary: Command-line to read metadata produced by FME scripts of Isogeo Scan, convert it into Isogeo model, apply rules and export it to a database or Isogeo.
Home-page: https://github.com/isogeo/scan-metadata-processor/
Author: Isogeo
Author-email: contact@isogeo.com
License: UNKNOWN
Project-URL: Docs, http://help.isogeo.com/scan/isogeo-scan-metadata-processor/
Project-URL: Bug Reports, https://github.com/isogeo/scan-metadata-processor/issues/
Project-URL: Source, https://github.com/isogeo/scan-metadata-processor/
Keywords: Isogeo scan JSON middleware
Platform: UNKNOWN
Classifier: Intended Audience :: Developers
Classifier: Intended Audience :: Information Technology
Classifier: Programming Language :: Python :: 3
Classifier: Programming Language :: Python :: 3.6
Classifier: Programming Language :: Python :: 3.7
Classifier: Programming Language :: Python :: 3.8
Classifier: Development Status :: 5 - Production/Stable
Classifier: Operating System :: OS Independent
Classifier: Topic :: Software Development :: Libraries :: Python Modules
Requires-Python: >=3.6, <4
Requires-Dist: click (==7.1.*)
Requires-Dist: geojson (<2.6,>=2.5)
Requires-Dist: isogeo-pysdk (<3.5,>=3.4)
Requires-Dist: python-dotenv (<0.14,>=0.12)
Requires-Dist: semver (<2.11,>=2.9)
Requires-Dist: Send2Trash (==1.5.*)
Provides-Extra: db-elastic
Requires-Dist: elasticsearch (<7.7,>=7.5) ; extra == 'db-elastic'
Provides-Extra: dev
Requires-Dist: black ; extra == 'dev'
Requires-Dist: flake8 ; extra == 'dev'
Provides-Extra: test
Requires-Dist: pytest ; extra == 'test'
Requires-Dist: pytest-cov ; extra == 'test'
